Metadata-Version: 2.1
Name: odoo13-addon-stock-vertical-lift-empty-tray-check
Version: 13.0.1.1.0
Summary: Checks if the tray is actually empty.
Home-page: https://github.com/OCA/stock-logistics-warehouse
Author: Camptocamp, Odoo Community Association (OCA)
Author-email: support@odoo-community.org
License: AGPL-3
Platform: UNKNOWN
Classifier: Programming Language :: Python
Classifier: Framework :: Odoo
Classifier: License :: OSI Approved :: GNU Affero General Public License v3
Classifier: Development Status :: 3 - Alpha
Requires-Python: >=3.5
Requires-Dist: odoo13-addon-stock-vertical-lift
Requires-Dist: odoo (<13.1dev,>=13.0a)
